flet/__init__.py
flet/auth/__init__.py
flet/auth/providers/__init__.py
flet/canvas/__init__.py
flet/map/__init__.py
flet/matplotlib_chart.py
flet/plotly_chart.py
flet/security/__init__.py
flet/utils/__init__.py
flet/version.py
flet_embed-0.24.1.dist-info/METADATA
flet_embed-0.24.1.dist-info/WHEEL
flet_embed-0.24.1.dist-info/RECORD
